numex/__init__.py
numex/_version.py
numex/gui_tk_mpl.py
numex/interactive_tk_mpl.py
numex/plugins/__init__.py
numex/plugins/io_bart_cfl.py
numex/plugins/io_matlab.py
numex/plugins/io_nibabel.py
numex/plugins/io_numpy.py
numex/plugins/synthetic.py
numex/resources/__init__.py
numex-0.0.0.7.data/data/share/icons/numex_logo.svg
numex-0.0.0.7.dist-info/DESCRIPTION.rst
numex-0.0.0.7.dist-info/METADATA
numex-0.0.0.7.dist-info/RECORD
numex-0.0.0.7.dist-info/WHEEL
numex-0.0.0.7.dist-info/entry_points.txt
numex-0.0.0.7.dist-info/metadata.json
numex-0.0.0.7.dist-info/top_level.txt
